voronout/Boundary.py
voronout/Point.py
voronout/VoronoiDiagram.py
voronout/VoronoiDiagramToJSON.py
voronout/__init__.py
voronout/edges/VoronoiEdge.py
voronout/edges/VoronoiEdgeData.py
voronout/edges/__init__.py
voronout/jsonOut/VoronoiJSONEncoder.py
voronout/jsonOut/__init__.py
voronout/jsonOut/tests/__init__.py
voronout/jsonOut/tests/voronoi_json_encoder_test.py
voronout/regions/VoronoiRegion.py
voronout/regions/VoronoiRegionData.py
voronout/regions/__init__.py
voronout/regions/tests/__init__.py
voronout/regions/tests/voronoi_region_data_test.py
voronout/tests/__init__.py
voronout/tests/boundary_test.py
voronout/tests/point_test.py
voronout/tests/voronoi_diagram_test.py
voronout/tests/voronoi_diagram_to_json_test.py
voronout/tests/voronoi_edge_test.py
voronout/tests/voronoi_region_test.py
voronout/utils/BoundValue.py
voronout/utils/__init__.py
voronout/utils/tests/__init__.py
voronout/utils/tests/bound_test.py
voronout-0.0.4.0.1.dist-info/METADATA
voronout-0.0.4.0.1.dist-info/WHEEL
voronout-0.0.4.0.1.dist-info/RECORD
