Metadata-Version: 2.4
Name: Voronout
Version: 0.0.4.0.1
Summary: Translating scipy.spatial's Voronoi diagrams into a set of cells bounded by a specified containing box, in easy-to-parse JSON.
Project-URL: Homepage, https://github.com/jpshankar/voronout
Project-URL: Issues, https://github.com/jpshankar/voronout/issues
Author-email: Javas Shankar <javasshankar@gmail.com>
License-Expression: MIT
Classifier: Operating System :: OS Independent
Classifier: Programming Language :: Python :: 3
Requires-Python: >=3.13
Requires-Dist: numpy
Requires-Dist: scipy
